[
  {
    "chunk": "Aromatic beef curry recipe A quick and simple beef and spinach curry with mild spices and rice. A great recipe for the rest of the family too! Freeze the extra portions for handy future meals. Age: 10 to 12 months Prep: 10 mins Cook: 30 mins Portions: 4 Ingredients - ¼ medium onion, peeled - ¼ small tomato - 160g diced beef - 1 tsp vegetable oil - ½ tbsp tomato purée - ¼ tsp ground turmeric - ¼ tsp (or pinch) mild chilli powder - ¼ tsp mild curry powder - 150ml water - 40g Spinach - 15g white rice - 1 tbsp frozen peas Method Chop the onion and tomatoes. Heat oil in pan and add the diced beef. Cook until browned. Then add the onion and tomatoes and cook for 5 minutes. Add the tomato purée, turmeric, chilli powder, curry powder and water. Bring to the boil,",
    "chunk_id": "aromatic_beef_curry_0",
    "title": "Aromatic Beef Curry",
    "description": "A quick and simple beef and spinach curry with mild spices and rice. A great recipe for the rest of the family too! Freeze the extra portions for handy future meals.",
    "source_url": "https://www.nhs.uk/start-for-life/baby/recipes-and-meal-ideas/aromatic-beef-curry/",
    "scraped_at": "2025-04-04T07:45:08.066362",
    "tokens": 195,
    "age_range": "10 to 12 months",
    "prep_time": "10 mins",
    "cook_time": "30 mins",
    "portions": 4,
    "ingredients": [
      "¼ medium onion, peeled",
      "¼ small tomato",
      "160g diced beef",
      "1 tsp vegetable oil",
      "½ tbsp tomato purée",
      "¼ tsp ground turmeric",
      "¼ tsp (or pinch) mild chilli powder",
      "¼ tsp mild curry powder",
      "150ml water",
      "40g Spinach",
      "15g white rice",
      "1 tbsp frozen peas"
    ],
    "weaning_tip": null,
    "meal_type": "unknown"
  },
  {
    "chunk": "beef. Cook until browned. Then add the onion and tomatoes and cook for 5 minutes. Add the tomato purée, turmeric, chilli powder, curry powder and water. Bring to the boil, cover and simmer gently for 15 to 20 minutes until the beef is cooked through and tender. Add a little extra water during cooking if needed. Meanwhile, in a separate pan of water add the rice and cook for approx. 10 minutes until cooked. Then drain. While the curry and rice are cooking, bring a small saucepan of water to the boil, add the peas and cook for around 6 minutes until soft. You can microwave if preferred. Roughly chop the spinach, add to the curry pan and cook for a further 3 or 4 minutes. Chop or mince the cooked curry with cooked rice. Serve ¼ of the curry in a bowl with a spoon/fork with the rice and",
    "chunk_id": "aromatic_beef_curry_1",
    "title": "Aromatic Beef Curry",
    "description": "A quick and simple beef and spinach curry with mild spices and rice. A great recipe for the rest of the family too! Freeze the extra portions for handy future meals.",
    "source_url": "https://www.nhs.uk/start-for-life/baby/recipes-and-meal-ideas/aromatic-beef-curry/",
    "scraped_at": "2025-04-04T07:45:08.066378",
    "tokens": 195,
    "age_range": "10 to 12 months",
    "prep_time": "10 mins",
    "cook_time": "30 mins",
    "portions": 4,
    "ingredients": [
      "¼ medium onion, peeled",
      "¼ small tomato",
      "160g diced beef",
      "1 tsp vegetable oil",
      "½ tbsp tomato purée",
      "¼ tsp ground turmeric",
      "¼ tsp (or pinch) mild chilli powder",
      "¼ tsp mild curry powder",
      "150ml water",
      "40g Spinach",
      "15g white rice",
      "1 tbsp frozen peas"
    ],
    "weaning_tip": null,
    "meal_type": "unknown"
  },
  {
    "chunk": "a further 3 or 4 minutes. Chop or mince the cooked curry with cooked rice. Serve ¼ of the curry in a bowl with a spoon/fork with the rice and cooked peas on the side as a finger food. Try serving with a spoon of full-fat yoghurt.",
    "chunk_id": "aromatic_beef_curry_2",
    "title": "Aromatic Beef Curry",
    "description": "A quick and simple beef and spinach curry with mild spices and rice. A great recipe for the rest of the family too! Freeze the extra portions for handy future meals.",
    "source_url": "https://www.nhs.uk/start-for-life/baby/recipes-and-meal-ideas/aromatic-beef-curry/",
    "scraped_at": "2025-04-04T07:45:08.066390",
    "tokens": 61,
    "age_range": "10 to 12 months",
    "prep_time": "10 mins",
    "cook_time": "30 mins",
    "portions": 4,
    "ingredients": [
      "¼ medium onion, peeled",
      "¼ small tomato",
      "160g diced beef",
      "1 tsp vegetable oil",
      "½ tbsp tomato purée",
      "¼ tsp ground turmeric",
      "¼ tsp (or pinch) mild chilli powder",
      "¼ tsp mild curry powder",
      "150ml water",
      "40g Spinach",
      "15g white rice",
      "1 tbsp frozen peas"
    ],
    "weaning_tip": null,
    "meal_type": "unknown"
  }
]