[
  {
    "chunk": "Beetroot dip with pitta bread fingers A colourful dish to excite your baby and introduce them to new textures and flavours. This dip is also great for older children with some chopped vegetable sticks to go with it. Age: 6 months or older Prep: 10 mins Cook: 15 mins Portions: 7 (approx) Ingredients - 1 medium beetroot, peeled and chopped (130g) - Half tsp ground cumin - 2 to 3 sprigs of fresh mint (4g) – optional - 1 tsp lemon juice - 1 tbsp crème fraiche - 1 tbsp cream cheese - Half a mini pitta bread, cut into finger slices (1 portion) Method Peel and chop the beetroot. Place in a pan, bring to the boil then simmer for 10 to 15 minutes (or until tender). Once cooked, strain and leave to cool. In a bowl mix the cumin, mint (if using), lemon juice, crème fraiche and cream",
    "chunk_id": "beetroot_dip_with_pitta_bread_fingers_0",
    "title": "Beetroot Dip With Pitta Bread Fingers",
    "description": "A colourful dish to excite your baby and introduce them to new textures and flavours. This dip is also great for older children with some chopped vegetable sticks to go with it.",
    "source_url": "https://www.nhs.uk/start-for-life/baby/recipes-and-meal-ideas/beetroot-dip-with-pitta-bread-fingers/",
    "scraped_at": "2025-04-04T07:45:13.301552",
    "tokens": 195,
    "age_range": "6 months or older",
    "prep_time": "10 mins",
    "cook_time": "15 mins",
    "portions": 7,
    "ingredients": [
      "1 medium beetroot, peeled and chopped (130g)",
      "Half tsp ground cumin",
      "2 to 3 sprigs of fresh mint (4g) – optional",
      "1 tsp lemon juice",
      "1 tbsp crème fraiche",
      "1 tbsp cream cheese",
      "Half a mini pitta bread, cut into finger slices (1 portion)"
    ],
    "weaning_tip": null,
    "meal_type": "unknown"
  },
  {
    "chunk": "for 10 to 15 minutes (or until tender). Once cooked, strain and leave to cool. In a bowl mix the cumin, mint (if using), lemon juice, crème fraiche and cream cheese together. Blend the cooled beetroot and mix with the crème fraiche mixture before serving. Cut the pitta bread into fingers. Serve alongside the bowl of beetroot for dipping. Store any leftovers in an airtight container in the fridge. Try using wholemeal pitta bread instead of white.",
    "chunk_id": "beetroot_dip_with_pitta_bread_fingers_1",
    "title": "Beetroot Dip With Pitta Bread Fingers",
    "description": "A colourful dish to excite your baby and introduce them to new textures and flavours. This dip is also great for older children with some chopped vegetable sticks to go with it.",
    "source_url": "https://www.nhs.uk/start-for-life/baby/recipes-and-meal-ideas/beetroot-dip-with-pitta-bread-fingers/",
    "scraped_at": "2025-04-04T07:45:13.301572",
    "tokens": 100,
    "age_range": "6 months or older",
    "prep_time": "10 mins",
    "cook_time": "15 mins",
    "portions": 7,
    "ingredients": [
      "1 medium beetroot, peeled and chopped (130g)",
      "Half tsp ground cumin",
      "2 to 3 sprigs of fresh mint (4g) – optional",
      "1 tsp lemon juice",
      "1 tbsp crème fraiche",
      "1 tbsp cream cheese",
      "Half a mini pitta bread, cut into finger slices (1 portion)"
    ],
    "weaning_tip": null,
    "meal_type": "unknown"
  }
]