[
  {
    "chunk": "Cheesy toast fingers and cucumber recipe Tasty cream cheese toast fingers, served with cucumber slices – a great finger food combo. Age: 6 months or older Prep: 5 mins Cook: 2 mins Portions: 2 (approx) Ingredients - 1 small slice wholemeal bread - 1 tsp full-fat cream cheese - 2 finger-sized sticks of cucumber (washed, skin removed and halved lengthways) Method Toast or grill the bread, then evenly spread the full-fat cream cheese. Slice into finger shapes, big enough for your baby to grasp with half sticking out the top of their hand. Serve with the cucumber sticks. Information: Use pitta bread, plain bagel, English muffin or crumpets as alternatives.",
    "chunk_id": "cheesy_toast_fingers_and_cucumber_0",
    "title": "Cheesy Toast Fingers And Cucumber",
    "description": "Tasty cream cheese toast fingers, served with cucumber slices – a great finger food combo.",
    "source_url": "https://www.nhs.uk/start-for-life/baby/recipes-and-meal-ideas/cheesy-toast-fingers-and-cucumber/",
    "scraped_at": "2025-04-04T07:45:19.698988",
    "tokens": 143,
    "age_range": "6 months or older",
    "prep_time": "5 mins",
    "cook_time": "2 mins",
    "portions": 2,
    "ingredients": [
      "1 small slice wholemeal bread",
      "1 tsp full-fat cream cheese",
      "2 finger-sized sticks of cucumber (washed, skin removed and halved lengthways)"
    ],
    "weaning_tip": null,
    "meal_type": "unknown"
  }
]