[
  {
    "chunk": "Jamaican fish curry recipe This Jamaican fish curry is full of flavours for your baby to explore, including cod, curry powder and plantain that can be enjoyed by the rest of the family too. Freeze the extra portions for handy future meals. Age: 7 to 9 months Prep: 10 mins Cook: 25 mins Portions: 4 (approx) Ingredients - ¼ small potato, peeled (25g) - ⅓ small onion, peeled (20g) - ½ small red pepper, deseeded (30g) - ½ garlic clove, peeled - 1 heaped tbsp plantain, peeled (20g) - ½ large cod (90g) - 1 tsp vegetable oil - 75ml water - ½ tsp curry powder - 70g tinned chopped tomatoes - 1 tbsp frozen peas (20g) - 15g white rice (1 portion) Method Dice the potatoes. Boil for 10 to 15 minutes in unsalted water until cooked. Then drain. Meanwhile, chop the onions, peppers, garlic and plantain. Cut the",
    "chunk_id": "jamaican_fish_curry_0",
    "title": "Jamaican Fish Curry",
    "description": "This Jamaican fish curry is full of flavours for your baby to explore, including cod, curry powder and plantain that can be enjoyed by the rest of the family too. Freeze the extra portions for handy future meals.",
    "source_url": "https://www.nhs.uk/start-for-life/baby/recipes-and-meal-ideas/jamaican-fish-curry/",
    "scraped_at": "2025-04-04T07:45:07.636091",
    "tokens": 195,
    "age_range": "7 to 9 months",
    "prep_time": "10 mins",
    "cook_time": "25 mins",
    "portions": 4,
    "ingredients": [
      "¼ small potato, peeled (25g)",
      "⅓ small onion, peeled (20g)",
      "½ small red pepper, deseeded (30g)",
      "½ garlic clove, peeled",
      "1 heaped tbsp plantain, peeled (20g)",
      "½ large cod (90g)",
      "1 tsp vegetable oil",
      "75ml water",
      "½ tsp curry powder",
      "70g tinned chopped tomatoes",
      "1 tbsp frozen peas (20g)",
      "15g white rice (1 portion)"
    ],
    "weaning_tip": null,
    "meal_type": "unknown"
  },
  {
    "chunk": "rice (1 portion) Method Dice the potatoes. Boil for 10 to 15 minutes in unsalted water until cooked. Then drain. Meanwhile, chop the onions, peppers, garlic and plantain. Cut the fish into chunks, removing any bones. Heat the oil in a pan, add the onions and peppers and cook for 5 minutes until softened. Stir in garlic, water, curry powder, tomatoes and plantain. Bring to the boil, then reduce the heat and simmer for 5 minutes until slightly thickened. Add the peas, fish and potatoes. Cook gently for a further 5 to 10 minutes until the fish is cooked. In the meantime, bring a pan of water to the boil and cook the rice for 15 to 20 minutes. Then drain. Mash or blend the curry with the cooked rice until its smooth with soft lumps – check thoroughly for bones. Serve quarter of the fish curry in a bowl.",
    "chunk_id": "jamaican_fish_curry_1",
    "title": "Jamaican Fish Curry",
    "description": "This Jamaican fish curry is full of flavours for your baby to explore, including cod, curry powder and plantain that can be enjoyed by the rest of the family too. Freeze the extra portions for handy future meals.",
    "source_url": "https://www.nhs.uk/start-for-life/baby/recipes-and-meal-ideas/jamaican-fish-curry/",
    "scraped_at": "2025-04-04T07:45:07.636108",
    "tokens": 195,
    "age_range": "7 to 9 months",
    "prep_time": "10 mins",
    "cook_time": "25 mins",
    "portions": 4,
    "ingredients": [
      "¼ small potato, peeled (25g)",
      "⅓ small onion, peeled (20g)",
      "½ small red pepper, deseeded (30g)",
      "½ garlic clove, peeled",
      "1 heaped tbsp plantain, peeled (20g)",
      "½ large cod (90g)",
      "1 tsp vegetable oil",
      "75ml water",
      "½ tsp curry powder",
      "70g tinned chopped tomatoes",
      "1 tbsp frozen peas (20g)",
      "15g white rice (1 portion)"
    ],
    "weaning_tip": null,
    "meal_type": "unknown"
  },
  {
    "chunk": "drain. Mash or blend the curry with the cooked rice until its smooth with soft lumps – check thoroughly for bones. Serve quarter of the fish curry in a bowl. Try serving with brown rice sometimes instead of white. Weaning tip Give your baby sips of water with their meals - rather than sweet drinks which can cause tooth decay.",
    "chunk_id": "jamaican_fish_curry_2",
    "title": "Jamaican Fish Curry",
    "description": "This Jamaican fish curry is full of flavours for your baby to explore, including cod, curry powder and plantain that can be enjoyed by the rest of the family too. Freeze the extra portions for handy future meals.",
    "source_url": "https://www.nhs.uk/start-for-life/baby/recipes-and-meal-ideas/jamaican-fish-curry/",
    "scraped_at": "2025-04-04T07:45:07.636119",
    "tokens": 78,
    "age_range": "7 to 9 months",
    "prep_time": "10 mins",
    "cook_time": "25 mins",
    "portions": 4,
    "ingredients": [
      "¼ small potato, peeled (25g)",
      "⅓ small onion, peeled (20g)",
      "½ small red pepper, deseeded (30g)",
      "½ garlic clove, peeled",
      "1 heaped tbsp plantain, peeled (20g)",
      "½ large cod (90g)",
      "1 tsp vegetable oil",
      "75ml water",
      "½ tsp curry powder",
      "70g tinned chopped tomatoes",
      "1 tbsp frozen peas (20g)",
      "15g white rice (1 portion)"
    ],
    "weaning_tip": null,
    "meal_type": "unknown"
  }
]