[
  {
    "chunk": "Lentil pasta with broccoli recipe Your baby will love tucking into this creamy pasta with sauce. Quick to whip up, it's suitable for the whole family too. Freeze the extra 3 portions of sauce for handy future meals. Age: 10 to 12 months Prep: 20 mins Cook: 20 mins Portions: 4 Ingredients - ½ small onion, peeled (30g) - 1 small garlic clove, peeled - 1 broccoli spear (38g) - 1 tsp vegetable oil - 150g canned chopped tomatoes - pinch dried mixed herbs - 200ml water - 2 tbsp dried red lentils (30g) - 1 tsp full fat cream cheese (1 portion) - 15g white pasta (1 portion) - 1 piece baby corn (1 portion 25g) Method Chop the garlic and onion. Chop the broccoli floret. Heat the oil in a saucepan, add the onion and garlic and soften for 3 to 4 minutes. Add the broccoli, tomatoes, mixed",
    "chunk_id": "lentil_pasta_with_broccoli_0",
    "title": "Lentil Pasta With Broccoli",
    "description": "Your baby will love tucking into this creamy pasta with sauce. Quick to whip up, it's suitable for the whole family too. Freeze the extra 3 portions of sauce for handy future meals.",
    "source_url": "https://www.nhs.uk/start-for-life/baby/recipes-and-meal-ideas/lentil-pasta-with-broccoli/",
    "scraped_at": "2025-04-04T07:45:09.959662",
    "tokens": 195,
    "age_range": "10 to 12 months",
    "prep_time": "20 mins",
    "cook_time": "20 mins",
    "portions": 4,
    "ingredients": [
      "½ small onion, peeled (30g)",
      "1 small garlic clove, peeled",
      "1 broccoli spear (38g)",
      "1 tsp vegetable oil",
      "150g canned chopped tomatoes",
      "pinch dried mixed herbs",
      "200ml water",
      "2 tbsp dried red lentils (30g)",
      "1 tsp full fat cream cheese (1 portion)",
      "15g white pasta (1 portion)",
      "1 piece baby corn (1 portion 25g)"
    ],
    "weaning_tip": null,
    "meal_type": "unknown"
  },
  {
    "chunk": "garlic and onion. Chop the broccoli floret. Heat the oil in a saucepan, add the onion and garlic and soften for 3 to 4 minutes. Add the broccoli, tomatoes, mixed herbs, water and lentils and cook uncovered for 10 to 12 minutes. Add a little more water during cooking if needed. Meanwhile place the pasta in a small pan with cold water, bring to boil and cook for 10 to 12 minutes until pasta is soft. Whilst the lentils and pasta are cooking, bring a small saucepan of water to the boil, add the baby corn and cook for approx. 5 to 6 minutes until soft. Steam or microwave if preferred. Once cooked remove ¼ of the broccoli and tomato sauce and stir in the cream cheese. Mix the cooked pasta with half of the broccoli and lentil sauce. Chop or mince the dish. Serve in a bowl with baby",
    "chunk_id": "lentil_pasta_with_broccoli_1",
    "title": "Lentil Pasta With Broccoli",
    "description": "Your baby will love tucking into this creamy pasta with sauce. Quick to whip up, it's suitable for the whole family too. Freeze the extra 3 portions of sauce for handy future meals.",
    "source_url": "https://www.nhs.uk/start-for-life/baby/recipes-and-meal-ideas/lentil-pasta-with-broccoli/",
    "scraped_at": "2025-04-04T07:45:09.959680",
    "tokens": 195,
    "age_range": "10 to 12 months",
    "prep_time": "20 mins",
    "cook_time": "20 mins",
    "portions": 4,
    "ingredients": [
      "½ small onion, peeled (30g)",
      "1 small garlic clove, peeled",
      "1 broccoli spear (38g)",
      "1 tsp vegetable oil",
      "150g canned chopped tomatoes",
      "pinch dried mixed herbs",
      "200ml water",
      "2 tbsp dried red lentils (30g)",
      "1 tsp full fat cream cheese (1 portion)",
      "15g white pasta (1 portion)",
      "1 piece baby corn (1 portion 25g)"
    ],
    "weaning_tip": null,
    "meal_type": "unknown"
  },
  {
    "chunk": "sauce and stir in the cream cheese. Mix the cooked pasta with half of the broccoli and lentil sauce. Chop or mince the dish. Serve in a bowl with baby corn on the side as a finger food. Give your baby the spoon or fork and encourage them to feed themselves. Try leaving a few of pasta pieces whole as a finger food too.",
    "chunk_id": "lentil_pasta_with_broccoli_2",
    "title": "Lentil Pasta With Broccoli",
    "description": "Your baby will love tucking into this creamy pasta with sauce. Quick to whip up, it's suitable for the whole family too. Freeze the extra 3 portions of sauce for handy future meals.",
    "source_url": "https://www.nhs.uk/start-for-life/baby/recipes-and-meal-ideas/lentil-pasta-with-broccoli/",
    "scraped_at": "2025-04-04T07:45:09.959693",
    "tokens": 83,
    "age_range": "10 to 12 months",
    "prep_time": "20 mins",
    "cook_time": "20 mins",
    "portions": 4,
    "ingredients": [
      "½ small onion, peeled (30g)",
      "1 small garlic clove, peeled",
      "1 broccoli spear (38g)",
      "1 tsp vegetable oil",
      "150g canned chopped tomatoes",
      "pinch dried mixed herbs",
      "200ml water",
      "2 tbsp dried red lentils (30g)",
      "1 tsp full fat cream cheese (1 portion)",
      "15g white pasta (1 portion)",
      "1 piece baby corn (1 portion 25g)"
    ],
    "weaning_tip": null,
    "meal_type": "unknown"
  }
]