[
  {
    "chunk": "Lynne Mum Tasty salmon risotto recipe A great recipe to introduce your baby to oily fish. It's quick and easy for the whole family too. Age: 12 months and older Prep: 10 mins Cook: 20 mins Portions: 1 Ingredients - ¼ onion, peeled - ½ garlic clove, peeled - 150ml water - 1 small salmon fillet (1/2 to serve) - 1 tsp vegetable oil - 1 ½ tbsp frozen peas - 25g white rice - 3 finger slices red pepper Method Preheat the oven to 200C, fan 180C, gas mark 5. Dice the onion and garlic. Place the salmon in an ovenproof dish and bake for 15 to 20 minutes, until cooked through. Meanwhile, heat the oil in a pan and add the onion and garlic. Cook for 1 minute. Add the rice, peas and water until the rice and vegetables are covered and stir. Cover and simmer gently until",
    "chunk_id": "lynne_0",
    "title": "Lynne",
    "description": "Mum",
    "source_url": "https://www.nhs.uk/start-for-life/baby/recipes-and-meal-ideas/tasty-salmon-risotto/",
    "scraped_at": "2025-04-04T07:45:09.664167",
    "tokens": 195,
    "age_range": "12 months and older",
    "prep_time": "10 mins",
    "cook_time": "20 mins",
    "portions": 1,
    "ingredients": [
      "¼ onion, peeled",
      "½ garlic clove, peeled",
      "150ml water",
      "1 small salmon fillet (1/2 to serve)",
      "1 tsp vegetable oil",
      "1 ½ tbsp frozen peas",
      "25g white rice",
      "3 finger slices red pepper"
    ],
    "weaning_tip": null,
    "meal_type": "unknown"
  },
  {
    "chunk": "and add the onion and garlic. Cook for 1 minute. Add the rice, peas and water until the rice and vegetables are covered and stir. Cover and simmer gently until the majority of the water has been absorbed and the rice is cooked, approx 10 minutes. Bring a small saucepan of water to the boil, add the red pepper strips and cook for about 5 minutes until soft. You can microwave if preferred. Check to see if the rice is cooked, if not, add more water and continue to simmer until cooked. Flake in half the salmon and combine well. Chop or mince the cooked risotto to the desired consistency. Serve with the cooked red pepper sticks as a finger food. Instead of baking fresh or frozen salmon, you can use tinned salmon (drained) flaked into the risotto. Family feedback This recipe is so easy to make with just a",
    "chunk_id": "lynne_1",
    "title": "Lynne",
    "description": "Mum",
    "source_url": "https://www.nhs.uk/start-for-life/baby/recipes-and-meal-ideas/tasty-salmon-risotto/",
    "scraped_at": "2025-04-04T07:45:09.664185",
    "tokens": 195,
    "age_range": "12 months and older",
    "prep_time": "10 mins",
    "cook_time": "20 mins",
    "portions": 1,
    "ingredients": [
      "¼ onion, peeled",
      "½ garlic clove, peeled",
      "150ml water",
      "1 small salmon fillet (1/2 to serve)",
      "1 tsp vegetable oil",
      "1 ½ tbsp frozen peas",
      "25g white rice",
      "3 finger slices red pepper"
    ],
    "weaning_tip": null,
    "meal_type": "unknown"
  },
  {
    "chunk": "food. Instead of baking fresh or frozen salmon, you can use tinned salmon (drained) flaked into the risotto. Family feedback This recipe is so easy to make with just a few ingredients and provides a good, healthy, tasty meal for my little boy. It's one of his favourites too!",
    "chunk_id": "lynne_2",
    "title": "Lynne",
    "description": "Mum",
    "source_url": "https://www.nhs.uk/start-for-life/baby/recipes-and-meal-ideas/tasty-salmon-risotto/",
    "scraped_at": "2025-04-04T07:45:09.664196",
    "tokens": 63,
    "age_range": "12 months and older",
    "prep_time": "10 mins",
    "cook_time": "20 mins",
    "portions": 1,
    "ingredients": [
      "¼ onion, peeled",
      "½ garlic clove, peeled",
      "150ml water",
      "1 small salmon fillet (1/2 to serve)",
      "1 tsp vegetable oil",
      "1 ½ tbsp frozen peas",
      "25g white rice",
      "3 finger slices red pepper"
    ],
    "weaning_tip": null,
    "meal_type": "unknown"
  }
]