[
  {
    "chunk": "Omelette muffins recipe Your baby will love feeding themselves these little pots of cheesy veg omelettes, served with potatoes and green beans. They're a great lunch for the rest of the family too! Age: 10 to 12 months Prep: 10 mins Cook: 20 mins Portions: 2 Ingredients - ½ tsp vegetable oil - ½ small onion, peeled (approx. 30g) - 20g full fat hard cheese - 30g frozen peas - pinch of mixed herbs - 1 large egg (approx. 60g) - Sprinkle of black pepper (optional) - 1 tsp water - 1 new potato (approx. 40g) - 25g trimmed green beans (approx. 8) Method Preheat the oven to 180C, 160C fan, gas mark 4. Very lightly grease the holes of a muffin tin with vegetable oil. Finely chop the onion and divide equally between the two muffin tin holes. Put in the oven for 5 minutes. Put the peas into",
    "chunk_id": "omelette_muffins_0",
    "title": "Omelette Muffins",
    "description": "Your baby will love feeding themselves these little pots of cheesy veg omelettes, served with potatoes and green beans. They're a great lunch for the rest of the family too!",
    "source_url": "https://www.nhs.uk/start-for-life/baby/recipes-and-meal-ideas/omelette-muffins/",
    "scraped_at": "2025-04-04T07:45:09.083731",
    "tokens": 195,
    "age_range": "10 to 12 months",
    "prep_time": "10 mins",
    "cook_time": "20 mins",
    "portions": 2,
    "ingredients": [
      "½ tsp vegetable oil",
      "½ small onion, peeled (approx. 30g)",
      "20g full fat hard cheese",
      "30g frozen peas",
      "pinch of mixed herbs",
      "1 large egg (approx. 60g)",
      "Sprinkle of black pepper (optional)",
      "1 tsp water",
      "1 new potato (approx. 40g)",
      "25g trimmed green beans (approx. 8)"
    ],
    "weaning_tip": null,
    "meal_type": "unknown"
  },
  {
    "chunk": "a muffin tin with vegetable oil. Finely chop the onion and divide equally between the two muffin tin holes. Put in the oven for 5 minutes. Put the peas into a bowl and add the grated cheese and herbs. Add the eggs, black pepper and water to the bowl, and mix with a fork. Remove the muffin tin from the oven, divide the mixture between the holes and gently stir. Return to the oven for 15 minutes or until golden brown on the top. Whilst the omelette muffins are cooking add the new potatoes to a saucepan of water, bring to the boil, and cook for 5 minutes. Add the green beans to the pan then cook for a further 5 minutes until potatoes and beans are soft. Allow the omelette muffins to cool for 5 minutes before removing from the tin. Chop or mince the omelettes to the desired",
    "chunk_id": "omelette_muffins_1",
    "title": "Omelette Muffins",
    "description": "Your baby will love feeding themselves these little pots of cheesy veg omelettes, served with potatoes and green beans. They're a great lunch for the rest of the family too!",
    "source_url": "https://www.nhs.uk/start-for-life/baby/recipes-and-meal-ideas/omelette-muffins/",
    "scraped_at": "2025-04-04T07:45:09.083749",
    "tokens": 195,
    "age_range": "10 to 12 months",
    "prep_time": "10 mins",
    "cook_time": "20 mins",
    "portions": 2,
    "ingredients": [
      "½ tsp vegetable oil",
      "½ small onion, peeled (approx. 30g)",
      "20g full fat hard cheese",
      "30g frozen peas",
      "pinch of mixed herbs",
      "1 large egg (approx. 60g)",
      "Sprinkle of black pepper (optional)",
      "1 tsp water",
      "1 new potato (approx. 40g)",
      "25g trimmed green beans (approx. 8)"
    ],
    "weaning_tip": null,
    "meal_type": "unknown"
  },
  {
    "chunk": "5 minutes until potatoes and beans are soft. Allow the omelette muffins to cool for 5 minutes before removing from the tin. Chop or mince the omelettes to the desired consistency, or slice and serve as a finger food. Serve with potatoes and green beans. Cover or wrap the remaining portions and refrigerate for the next day. Swap the green beans for other vegetables you have at home such as courgette or broccoli fingers, frozen mixed veg or pepper strips.",
    "chunk_id": "omelette_muffins_2",
    "title": "Omelette Muffins",
    "description": "Your baby will love feeding themselves these little pots of cheesy veg omelettes, served with potatoes and green beans. They're a great lunch for the rest of the family too!",
    "source_url": "https://www.nhs.uk/start-for-life/baby/recipes-and-meal-ideas/omelette-muffins/",
    "scraped_at": "2025-04-04T07:45:09.083760",
    "tokens": 104,
    "age_range": "10 to 12 months",
    "prep_time": "10 mins",
    "cook_time": "20 mins",
    "portions": 2,
    "ingredients": [
      "½ tsp vegetable oil",
      "½ small onion, peeled (approx. 30g)",
      "20g full fat hard cheese",
      "30g frozen peas",
      "pinch of mixed herbs",
      "1 large egg (approx. 60g)",
      "Sprinkle of black pepper (optional)",
      "1 tsp water",
      "1 new potato (approx. 40g)",
      "25g trimmed green beans (approx. 8)"
    ],
    "weaning_tip": null,
    "meal_type": "unknown"
  }
]