[
  {
    "chunk": "Pea and ham bake This easy-to-prepare pasta bake will make a popular dinner. It can be enjoyed by the rest of the family too – simply serve as it is instead of blending or mashing. Age: 7 to 9 months Prep: 10 mins Cook: 20 to 30 mins Portions: 4 (approx) Ingredients - 100g white pasta - 2 mushrooms (35g) - 1/2 small onion, peeled (35g) - 1 garlic clove, peeled and crushed - 1/2 tbsp fresh basil - 40g ham - 1 tsp vegetable oil - 100g tinned chopped tomatoes (1/4 can) - 1 tsp tomato puree - 40g frozen peas - 50ml water Method Preheat the oven to 180°C / 350°F / Gas Mark 4. Bring a pan of water to the boil, cook the pasta for 10 to 12 minutes until soft. When cooked, drain and place in an oven proof dish, make sure the pasta only",
    "chunk_id": "pea_and_ham_bake_0",
    "title": "Pea And Ham Bake",
    "description": "This easy-to-prepare pasta bake will make a popular dinner. It can be enjoyed by the rest of the family too – simply serve as it is instead of blending or mashing.",
    "source_url": "https://www.nhs.uk/start-for-life/baby/recipes-and-meal-ideas/pea-and-ham-bake/",
    "scraped_at": "2025-04-04T07:45:12.113054",
    "tokens": 195,
    "age_range": "7 to 9 months",
    "prep_time": "10 mins",
    "cook_time": "20 to 30 mins",
    "portions": 4,
    "ingredients": [
      "100g white pasta",
      "2 mushrooms (35g)",
      "1/2 small onion, peeled (35g)",
      "1 garlic clove, peeled and crushed",
      "1/2 tbsp fresh basil",
      "40g ham",
      "1 tsp vegetable oil",
      "100g tinned chopped tomatoes (1/4 can)",
      "1 tsp tomato puree",
      "40g frozen peas",
      "50ml water"
    ],
    "weaning_tip": null,
    "meal_type": "unknown"
  },
  {
    "chunk": "of water to the boil, cook the pasta for 10 to 12 minutes until soft. When cooked, drain and place in an oven proof dish, make sure the pasta only half-fills the dish. Chop the mushrooms, onions, garlic, basil and ham. Heat the oil in a saucepan and add the onions, garlic and mushrooms until softened (2 to 3 minutes). Add the chopped tomatoes, tomato purée, water and peas – stir, cover and simmer for 5 to 10 minutes (until the sauce has thickened slightly). Add the basil and diced ham. Allow to cool. Blend or mash the pasta bake until smooth with soft lumps. Serve a quarter in a bowl with fork or spoon. Make it veggie by swapping the ham for soya pieces. Pour the sauce over the pasta and mix well. Place in the oven for 10 minutes. Weaning tip Give your baby sips of water with",
    "chunk_id": "pea_and_ham_bake_1",
    "title": "Pea And Ham Bake",
    "description": "This easy-to-prepare pasta bake will make a popular dinner. It can be enjoyed by the rest of the family too – simply serve as it is instead of blending or mashing.",
    "source_url": "https://www.nhs.uk/start-for-life/baby/recipes-and-meal-ideas/pea-and-ham-bake/",
    "scraped_at": "2025-04-04T07:45:12.113072",
    "tokens": 195,
    "age_range": "7 to 9 months",
    "prep_time": "10 mins",
    "cook_time": "20 to 30 mins",
    "portions": 4,
    "ingredients": [
      "100g white pasta",
      "2 mushrooms (35g)",
      "1/2 small onion, peeled (35g)",
      "1 garlic clove, peeled and crushed",
      "1/2 tbsp fresh basil",
      "40g ham",
      "1 tsp vegetable oil",
      "100g tinned chopped tomatoes (1/4 can)",
      "1 tsp tomato puree",
      "40g frozen peas",
      "50ml water"
    ],
    "weaning_tip": null,
    "meal_type": "unknown"
  },
  {
    "chunk": "the ham for soya pieces. Pour the sauce over the pasta and mix well. Place in the oven for 10 minutes. Weaning tip Give your baby sips of water with their meals - rather than sweet drinks which can cause tooth decay.",
    "chunk_id": "pea_and_ham_bake_2",
    "title": "Pea And Ham Bake",
    "description": "This easy-to-prepare pasta bake will make a popular dinner. It can be enjoyed by the rest of the family too – simply serve as it is instead of blending or mashing.",
    "source_url": "https://www.nhs.uk/start-for-life/baby/recipes-and-meal-ideas/pea-and-ham-bake/",
    "scraped_at": "2025-04-04T07:45:12.113084",
    "tokens": 54,
    "age_range": "7 to 9 months",
    "prep_time": "10 mins",
    "cook_time": "20 to 30 mins",
    "portions": 4,
    "ingredients": [
      "100g white pasta",
      "2 mushrooms (35g)",
      "1/2 small onion, peeled (35g)",
      "1 garlic clove, peeled and crushed",
      "1/2 tbsp fresh basil",
      "40g ham",
      "1 tsp vegetable oil",
      "100g tinned chopped tomatoes (1/4 can)",
      "1 tsp tomato puree",
      "40g frozen peas",
      "50ml water"
    ],
    "weaning_tip": null,
    "meal_type": "unknown"
  }
]