[
  {
    "chunk": "Vegetable biryani A super easy but interesting one-pot meal using mixed vegetables, chickpeas, rice and curry powder. Age: 7 to 9 months Prep: 10 mins Cook: 25 mins Portions: 4 (approx) Ingredients - 1/3 small onion, peeled (20g) - 1/3 medium carrot, peeled (40g) - 2 cauliflower florets (35g) - 1 tsp vegetable oil - 1/2 tsp curry powder - 1 tbsp frozen peas (25g) - 2 tbsp canned chickpeas, no added sugar or salt, drained (80g) - 65g basmati rice - 175ml water Method Chop up the onion and carrot, break the cauliflower into florets. Heat the oil in a pan, add the curry powder and onion. Cook for a few minutes until the onion softens. Add the carrot, peas, cauliflower, chickpeas and rice – stir for 1 minute. Pour over the water, simmer gently with the lid on for 15 to 20 minutes until the rice is tender",
    "chunk_id": "vegetable_biryani_0",
    "title": "Vegetable Biryani",
    "description": "A super easy but interesting one-pot meal using mixed vegetables, chickpeas, rice and curry powder.",
    "source_url": "https://www.nhs.uk/start-for-life/baby/recipes-and-meal-ideas/vegetable-biryani/",
    "scraped_at": "2025-04-04T07:45:11.248360",
    "tokens": 195,
    "age_range": "7 to 9 months",
    "prep_time": "10 mins",
    "cook_time": "25 mins",
    "portions": 4,
    "ingredients": [
      "1/3 small onion, peeled (20g)",
      "1/3 medium carrot, peeled (40g)",
      "2 cauliflower florets (35g)",
      "1 tsp vegetable oil",
      "1/2 tsp curry powder",
      "1 tbsp frozen peas (25g)",
      "2 tbsp canned chickpeas, no added sugar or salt, drained (80g)",
      "65g basmati rice",
      "175ml water"
    ],
    "weaning_tip": null,
    "meal_type": "unknown"
  },
  {
    "chunk": "peas, cauliflower, chickpeas and rice – stir for 1 minute. Pour over the water, simmer gently with the lid on for 15 to 20 minutes until the rice is tender and the vegetables are cooked. Allow to cool. Blend or mash the biryani until it is smooth with soft lumps. Serve a quarter of it in a bowl. Serve with cooked cauliflower florets as a finger food. Weaning tip Give your baby sips of water with their meals - rather than sweet drinks which can cause tooth decay.",
    "chunk_id": "vegetable_biryani_1",
    "title": "Vegetable Biryani",
    "description": "A super easy but interesting one-pot meal using mixed vegetables, chickpeas, rice and curry powder.",
    "source_url": "https://www.nhs.uk/start-for-life/baby/recipes-and-meal-ideas/vegetable-biryani/",
    "scraped_at": "2025-04-04T07:45:11.248378",
    "tokens": 114,
    "age_range": "7 to 9 months",
    "prep_time": "10 mins",
    "cook_time": "25 mins",
    "portions": 4,
    "ingredients": [
      "1/3 small onion, peeled (20g)",
      "1/3 medium carrot, peeled (40g)",
      "2 cauliflower florets (35g)",
      "1 tsp vegetable oil",
      "1/2 tsp curry powder",
      "1 tbsp frozen peas (25g)",
      "2 tbsp canned chickpeas, no added sugar or salt, drained (80g)",
      "65g basmati rice",
      "175ml water"
    ],
    "weaning_tip": null,
    "meal_type": "unknown"
  }
]